clint/__init__.py
clint/cli/__init__.py
clint/cli/command.py
clint/cli/runner.py
clint/exceptions.py
clint/hook_handler/__init__.py
clint/hook_handler/exceptions.py
clint/hook_handler/hook_handler.py
clint/result/__init__.py
clint/result/exceptions.py
clint/result/result.py
clint/validator/__init__.py
clint/validator/commit.py
clint/validator/exceptions.py
clint/validator/footer.py
clint/validator/paragraph.py
clint/validator/subject.py
clint_cli-0.5.0.dist-info/entry_points.txt
clint_cli-0.5.0.dist-info/COPYING
clint_cli-0.5.0.dist-info/WHEEL
clint_cli-0.5.0.dist-info/METADATA
clint_cli-0.5.0.dist-info/RECORD
