Metadata-Version: 2.1
Name: clint-cli
Version: 0.5.0
Summary: Conventional Commits Linter
Home-page: https://github.com/rcisterna/clint
License: GPL-3.0-or-later
Author: Ricardo Cisterna
Author-email: r.cisternasantos@gmail.com
Requires-Python: >=3.7.2,<4.0
Classifier: Development Status :: 4 - Beta
Classifier: Environment :: Console
Classifier: Framework :: Pytest
Classifier: Intended Audience :: Developers
Classifier: License :: OSI Approved :: GNU General Public License v3 or later (GPLv3+)
Classifier: Operating System :: MacOS
Classifier: Operating System :: POSIX
Classifier: Programming Language :: Python
Classifier: Programming Language :: Python :: 3
Classifier: Programming Language :: Python :: 3.10
Classifier: Programming Language :: Python :: 3.7
Classifier: Programming Language :: Python :: 3.8
Classifier: Programming Language :: Python :: 3.9
Classifier: Topic :: Software Development :: Version Control :: Git
Classifier: Topic :: System :: Shells
Requires-Dist: click (>=8.1.3,<9.0.0)
Project-URL: Repository, https://github.com/rcisterna/clint
